certifyGUI/__init__.py
certifygui-0.2.1.dist-info/METADATA
certifygui-0.2.1.dist-info/WHEEL
certifygui-0.2.1.dist-info/top_level.txt
certifygui-0.2.1.dist-info/RECORD
