Metadata-Version: 2.4
Name: certifyGUI
Version: 0.2.1
Summary: Certificate Designer is a Python GUI tool that lets you visually design and generate personalized certificates from Excel data using a drag-and-drop interface. Built with Tkinter and Pillow, it supports live preview, font customization, and bulk certificate creation with zero coding required.
Home-page: https://github.com/MuthuKumaran-Dev-10000/certify
Author: Muthukumaran S
Author-email: muthukumarandeveloper@gmail.com
Classifier: Programming Language :: Python :: 3
Classifier: License :: OSI Approved :: MIT License
Requires-Python: >=3.6
Dynamic: author
Dynamic: author-email
Dynamic: classifier
Dynamic: description
Dynamic: description-content-type
Dynamic: home-page
Dynamic: requires-python
Dynamic: summary
